{
    "positions": [
        {
            "analyses": [
                {
                    "is_omitted": false,
                    "record_id": "26616-01",
                    "uuid": "20a7c39e-fa75-43fb-bd4b-ee514dfff683"
                },
                {
                    "is_omitted": false,
                    "record_id": "26616-02",
                    "uuid": "d171ab2b-fe47-41e8-b796-b680a85280c1"
                },
                {
                    "is_omitted": false,
                    "record_id": "26616-03",
                    "uuid": "4bb9cfa9-4139-4f05-bc13-7884ebc6d8f5"
                },
                {
                    "is_omitted": false,
                    "record_id": "26616-04",
                    "uuid": "4ff5ca6e-1655-4103-a8d8-f25906b3af9b"
                },
                {
                    "is_omitted": false,
                    "record_id": "26616-05",
                    "uuid": "fc275997-1096-491c-ba2f-85fb9e2333f9"
                },
                {
                    "is_omitted": false,
                    "record_id": "26616-06",
                    "uuid": "bde56b44-b0dd-41b2-8c10-7d98c4e8a55c"
                }
            ],
            "decay_constants": {
                "lambda_k_total": 5.463e-10,
                "lambda_k_total_error": 0
            },
            "identifier": "26616",
            "j": 0.0019103428241712766,
            "j_err": 5.234995098449717e-07,
            "mean_j": 0.0019101390094728263,
            "mean_j_err": 4.326748057437817e-07,
            "options": {
                "model_kind": "Plane",
                "monitor_age": 28.201,
                "monitor_material": "FC-2",
                "monitor_name": "FC-2",
                "monitor_reference": "FC Min",
                "monte_carlo_ntrials": 10000,
                "predicted_j_error_type": "SEM, but if MSWD>1 use SEM * sqrt(MSWD)",
                "use_monte_carlo": true,
                "use_weighted_fit": false
            },
            "position": 7,
            "position_jerr": 0.0
        },
        {
            "analyses": [
                {
                    "is_omitted": false,
                    "record_id": "26617-01",
                    "uuid": "168251b7-27b9-4bc3-b237-031e8cee4236"
                },
                {
                    "is_omitted": false,
                    "record_id": "26617-02",
                    "uuid": "953024ef-1f5e-43bb-ba1e-7a979ea410e6"
                },
                {
                    "is_omitted": false,
                    "record_id": "26617-03",
                    "uuid": "f25841b0-5265-4f1d-85f4-f0c46a66047e"
                },
                {
                    "is_omitted": false,
                    "record_id": "26617-04",
                    "uuid": "e048d600-5104-429b-942b-fbcc79f14480"
                },
                {
                    "is_omitted": false,
                    "record_id": "26617-05",
                    "uuid": "0a530c0b-2726-43ac-bcfb-a11beff4c693"
                },
                {
                    "is_omitted": false,
                    "record_id": "26617-06",
                    "uuid": "c5df84b3-0aed-4866-8663-04cc522d8312"
                }
            ],
            "decay_constants": {
                "lambda_k_total": 5.463e-10,
                "lambda_k_total_error": 0
            },
            "identifier": "26617",
            "j": 0.0019099853153034026,
            "j_err": 9.626245209577907e-07,
            "mean_j": 0.001910699904498791,
            "mean_j_err": 1.3717765763170706e-06,
            "options": {
                "model_kind": "Plane",
                "monitor_age": 28.201,
                "monitor_material": "FC-2",
                "monitor_name": "FC-2",
                "monitor_reference": "FC Min",
                "monte_carlo_ntrials": 10000,
                "predicted_j_error_type": "SEM, but if MSWD>1 use SEM * sqrt(MSWD)",
                "use_monte_carlo": true,
                "use_weighted_fit": false
            },
            "position": 8,
            "position_jerr": 0.0
        },
        {
            "analyses": [
                {
                    "is_omitted": false,
                    "record_id": "26618-01",
                    "uuid": "34acbad1-e099-49a4-b506-342d7caaac62"
                },
                {
                    "is_omitted": false,
                    "record_id": "26618-02",
                    "uuid": "a09d4984-1881-47a2-9098-6a10629e7655"
                },
                {
                    "is_omitted": false,
                    "record_id": "26618-03",
                    "uuid": "4a462ef9-d46c-4949-9903-b4c132e4ad80"
                },
                {
                    "is_omitted": false,
                    "record_id": "26618-04",
                    "uuid": "c3ba85bf-19b3-42ff-b9d8-639bc2dc3ec8"
                },
                {
                    "is_omitted": false,
                    "record_id": "26618-05",
                    "uuid": "a927ef26-3b7b-418b-b699-602c7c1d8829"
                },
                {
                    "is_omitted": false,
                    "record_id": "26618-06",
                    "uuid": "0813587c-e2fc-49df-9eb7-5dc029f9b855"
                }
            ],
            "decay_constants": {
                "lambda_k_total": 5.463e-10,
                "lambda_k_total_error": 0
            },
            "identifier": "26618",
            "j": 0.0019105485016294478,
            "j_err": 1.0920241627657983e-06,
            "mean_j": 0.0019094660216359722,
            "mean_j_err": 1.989535296598496e-06,
            "options": {
                "model_kind": "Plane",
                "monitor_age": 28.201,
                "monitor_material": "FC-2",
                "monitor_name": "FC-2",
                "monitor_reference": "FC Min",
                "monte_carlo_ntrials": 10000,
                "predicted_j_error_type": "SEM, but if MSWD>1 use SEM * sqrt(MSWD)",
                "use_monte_carlo": true,
                "use_weighted_fit": false
            },
            "position": 9,
            "position_jerr": 0.0
        },
        {
            "analyses": [
                {
                    "is_omitted": false,
                    "record_id": "26619-01",
                    "uuid": "cc89ea68-9ff0-4587-a92e-cf0609a84375"
                },
                {
                    "is_omitted": false,
                    "record_id": "26619-02",
                    "uuid": "54e92a97-5ada-4f7a-9831-d2f08aaf559d"
                },
                {
                    "is_omitted": false,
                    "record_id": "26619-03",
                    "uuid": "ae6d294b-c2a2-478d-aa00-9b1e11feca02"
                },
                {
                    "is_omitted": false,
                    "record_id": "26619-04",
                    "uuid": "95dbc0e7-ac0b-4f11-b801-e36c52b7b4e8"
                },
                {
                    "is_omitted": false,
                    "record_id": "26619-05",
                    "uuid": "a83cceb6-1f00-4a19-b86b-b41434103fc1"
                },
                {
                    "is_omitted": true,
                    "record_id": "26619-06",
                    "uuid": "592b2ff0-f0a4-4cef-ae0f-ee02ed759fa3"
                }
            ],
            "decay_constants": {
                "lambda_k_total": 5.463e-10,
                "lambda_k_total_error": 0
            },
            "identifier": "26619",
            "j": 0.0019115395951141228,
            "j_err": 7.051897590894743e-07,
            "mean_j": 0.0019124791914087453,
            "mean_j_err": 4.788919860586654e-07,
            "options": {
                "model_kind": "Plane",
                "monitor_age": 28.201,
                "monitor_material": "FC-2",
                "monitor_name": "FC-2",
                "monitor_reference": "FC Min",
                "monte_carlo_ntrials": 10000,
                "predicted_j_error_type": "SEM, but if MSWD>1 use SEM * sqrt(MSWD)",
                "use_monte_carlo": true,
                "use_weighted_fit": false
            },
            "position": 10,
            "position_jerr": 0.0
        },
        {
            "analyses": [
                {
                    "is_omitted": false,
                    "record_id": "26620-01",
                    "uuid": "210b72b8-1ed3-431a-b97a-c2a6b2388772"
                },
                {
                    "is_omitted": false,
                    "record_id": "26620-02",
                    "uuid": "99e1e8cc-8b7e-473a-bf01-6206bf239450"
                },
                {
                    "is_omitted": false,
                    "record_id": "26620-03",
                    "uuid": "503512d5-71f6-4e18-9d76-c2c9f39fb165"
                },
                {
                    "is_omitted": false,
                    "record_id": "26620-04",
                    "uuid": "093537ae-9fd1-40a3-b21c-fa1028765e4f"
                },
                {
                    "is_omitted": true,
                    "record_id": "26620-05",
                    "uuid": "057c4148-cafa-4d62-b9a4-9890013ef7db"
                },
                {
                    "is_omitted": false,
                    "record_id": "26620-06",
                    "uuid": "85f6f09e-f8b4-4f71-8306-53e2a78a1cb9"
                }
            ],
            "decay_constants": {
                "lambda_k_total": 5.463e-10,
                "lambda_k_total_error": 0
            },
            "identifier": "26620",
            "j": 0.0019118971039819967,
            "j_err": 3.0797954735508794e-07,
            "mean_j": 0.0019113968189972456,
            "mean_j_err": 2.063679391711654e-07,
            "options": {
                "model_kind": "Plane",
                "monitor_age": 28.201,
                "monitor_material": "FC-2",
                "monitor_name": "FC-2",
                "monitor_reference": "FC Min",
                "monte_carlo_ntrials": 10000,
                "predicted_j_error_type": "SEM, but if MSWD>1 use SEM * sqrt(MSWD)",
                "use_monte_carlo": true,
                "use_weighted_fit": false
            },
            "position": 11,
            "position_jerr": 0.0
        },
        {
            "analyses": [
                {
                    "is_omitted": false,
                    "record_id": "26621-01",
                    "uuid": "365f996e-0d18-4fbc-90ba-5a576f389dc1"
                },
                {
                    "is_omitted": false,
                    "record_id": "26621-02",
                    "uuid": "40f648ac-fe89-4ddd-92c3-f516e105d964"
                },
                {
                    "is_omitted": false,
                    "record_id": "26621-03",
                    "uuid": "41354e2a-15be-4753-a7d3-20134c027423"
                },
                {
                    "is_omitted": false,
                    "record_id": "26621-04",
                    "uuid": "0c17d931-aecc-4428-bc3f-d93ce0423857"
                },
                {
                    "is_omitted": false,
                    "record_id": "26621-05",
                    "uuid": "a1124404-09fd-418a-9af2-b1159ae55d18"
                },
                {
                    "is_omitted": false,
                    "record_id": "26621-06",
                    "uuid": "d36bfa27-5352-4126-a3bf-c0328fb09a80"
                }
            ],
            "decay_constants": {
                "lambda_k_total": 5.463e-10,
                "lambda_k_total_error": 0
            },
            "identifier": "26621",
            "j": 0.0019113339176559515,
            "j_err": 3.945852051454918e-07,
            "mean_j": 0.0019114663118426154,
            "mean_j_err": 3.365901997730131e-07,
            "options": {
                "model_kind": "Plane",
                "monitor_age": 28.201,
                "monitor_material": "FC-2",
                "monitor_name": "FC-2",
                "monitor_reference": "FC Min",
                "monte_carlo_ntrials": 10000,
                "predicted_j_error_type": "SEM, but if MSWD>1 use SEM * sqrt(MSWD)",
                "use_monte_carlo": true,
                "use_weighted_fit": false
            },
            "position": 12,
            "position_jerr": 0.0
        }
    ],
    "z": 19.0
}